dataloader_param_helper/__init__.py
dataloader_param_helper/core.py
dataloader_param_helper-0.1.1.dist-info/LICENSE
dataloader_param_helper-0.1.1.dist-info/METADATA
dataloader_param_helper-0.1.1.dist-info/WHEEL
dataloader_param_helper-0.1.1.dist-info/top_level.txt
dataloader_param_helper-0.1.1.dist-info/RECORD
