Metadata-Version: 2.1
Name: dataloader_param_helper
Version: 0.1.1
Summary: Finding the optimal parameters for a Dataloader.
Home-page: https://github.com/splendidz/dataloader_param_helper
Author: Soo Hwan Cho
Author-email: soohwancho@korea.ac.kr
Classifier: Programming Language :: Python :: 3
Classifier: License :: OSI Approved :: MIT License
Classifier: Operating System :: OS Independent
Requires-Python: >=3.7
License-File: LICENSE
